mailsuite/__init__.py
mailsuite/imap.py
mailsuite/smtp.py
mailsuite/utils.py
mailsuite-1.11.2.dist-info/METADATA
mailsuite-1.11.2.dist-info/WHEEL
mailsuite-1.11.2.dist-info/licenses/LICENSE
mailsuite-1.11.2.dist-info/RECORD
