Metadata-Version: 2.4
Name: mailsuite
Version: 1.11.2
Summary: A Python package for retrieving, parsing, and sending emails
Project-URL: Homepage, https://github.com/seanthegeek/mailsuite/
Project-URL: Documentation, https://seanthegeek.github.io/mailsuite/
Project-URL: Issues, https://github.com/seanthegeek/mailsuite/issues
Project-URL: Changelog, https://github.com/seanthegeek/mailsuite/blob/master/CHANGELOG.md
Author-email: Sean Whalen <whalenster@gmail.com>
License-Expression: Apache-2.0
License-File: LICENSE
Keywords: IMAP,SMTP,email
Classifier: Development Status :: 5 - Production/Stable
Classifier: Intended Audience :: Developers
Classifier: Intended Audience :: Information Technology
Classifier: License :: OSI Approved :: Apache Software License
Classifier: Operating System :: OS Independent
Classifier: Programming Language :: Python :: 3
Requires-Python: >=3.9
Requires-Dist: dnspython>=2.0.0
Requires-Dist: expiringdict==1.2.2
Requires-Dist: html2text>=2020.1.16
Requires-Dist: imapclient>=3.1.0
Requires-Dist: mail-parser>=4.1.2
Requires-Dist: publicsuffix2>=2.20190812
